{"date": "2021-12-02 11:47:07.159000+00:00", "ticker": "AMZN", "mrkt_info": {"open": 3507.07, "close": 3437.36}, "html": "<div class=\"storyContent\" lang=\"en\"><style type=\"text/css\">.storyContent * {border-color:inherit !important;outline-color:inherit !important;}</style><div class=\"tr-npp-lead\">\n<p>RNS Number : 3788UWANdisco Plc02 December 2021</p>\n</div>\n<div class=\"tr-npp-body\">\n<p>\n<span>01 December 2021</span>\n</p>\n<p>\n<span>WANdisco plc</span>\n</p>\n<p>\n<span>\n</span></p>\n<p>\n<span>(\" <span>WANdisco</span> \" or the \" <span>Company</span> \")</span>\n</p>\n<p>\n<span>\n</span></p>\n<p>\n<span>Block admission notification</span>\n</p>\n<p>\n<span>\n</span></p>\n<p>\n<span>WANdisco (WAND.L) the LiveData company, announces its block admission notification.</span>\n</p>\n<p>\n<span>\n</span></p>\n<div class=\"story-table-container\"><table class=\"story-basic-table\">\n<tbody>\n<tr>\n<td>\n<p>\n<span>Name of issuer:</span>\n</p>\n</td>\n<td>\n<p>\n<span>WANdisco plc</span>\n</p>\n</td>\n</tr>\n<tr>\n<td>\n<p>\n<span>Name of scheme(s):</span>\n</p>\n</td>\n<td>\n<p>\n<span>i. WANdisco plc UK Enterprise Management Incentive Plan 2012</span>\n</p>\n<p>\n<span>ii. WANdisco plc UK Unapproved Sub-Plan 2012</span>\n</p>\n<p>\n<span>iii. WANdisco plc US Sub-Plan 2012</span>\n</p>\n<p>\n<span>iv. WANdisco plc Long Term Incentive Plan 2013</span>\n</p>\n<p>\n<span>v. WANdisco plc US Equity Incentive Plan 2013</span>\n</p>\n<p>\n<span>vi. WANdisco plc UK EMI Sub-plan 2013</span>\n</p>\n</td>\n</tr>\n<tr>\n<td>\n<p>\n<span>Period of return:</span>\n</p>\n</td>\n<td>\n<p>\n<span>From: 01 June 2021 To: 30 November 2021</span>\n</p>\n</td>\n</tr>\n<tr>\n<td>\n<p>\n<span>Balance of unallotted securities under scheme(s) from previous return:</span>\n</p>\n</td>\n<td>\n<p>\n<span>Ordinary Shares of 10p each as follows:</span>\n</p>\n<p>\n<span>i. 227,517</span>\n</p>\n<p>\n<span>ii. 88,685</span>\n</p>\n<p>\n<span>iii. 293,334</span>\n</p>\n<p>\n<span>iv. 75,455</span>\n</p>\n<p>\n<span>v. 1,097,562</span>\n</p>\n<p>\n<span>vi. 443,615</span>\n</p>\n</td>\n</tr>\n<tr>\n<td>\n<p>\n<span>Plus: The amount by which the block scheme(s) has been increased (decreased) since the last return:</span>\n</p>\n</td>\n<td>\n<p>\n<span>\n</span></p>\n<p>\n<span>i. nil</span>\n</p>\n<p>\n<span>ii. nil</span>\n</p>\n<p>\n<span>iii. nil</span>\n</p>\n<p>\n<span>iv. nil</span>\n</p>\n<p>\n<span>v. nil</span>\n</p>\n<p>\n<span>vi. nil</span>\n</p>\n</td>\n</tr>\n<tr>\n<td>\n<p>\n<span>Less: Number of securities issued under the scheme(s) during the period:</span>\n</p>\n</td>\n<td>\n<p>\n<span>\n</span></p>\n<p>\n<span>i. nil</span>\n</p>\n<p>\n<span>ii. 88,685</span>\n</p>\n<p>\n<span>iii. 25,000</span>\n</p>\n<p>\n<span>iv. nil</span>\n</p>\n<p>\n<span>v. nil</span>\n</p>\n<p>\n<span>vi. nil</span>\n</p>\n</td>\n</tr>\n<tr>\n<td>\n<p>\n<span>Equals: Balance under the scheme(s) of securities not yet issued at the end of the period:</span>\n</p>\n</td>\n<td>\n<p>\n<span>\n</span></p>\n<p>\n<span>i. 227,517</span>\n</p>\n<p>\n<span>ii. nil</span>\n</p>\n<p>\n<span>iii. 268,334</span>\n</p>\n<p>\n<span>iv. 75,455</span>\n</p>\n<p>\n<span>v. 1,097,562</span>\n</p>\n<p>\n<span>vi. 443,615</span>\n</p>\n</td>\n</tr>\n<tr>\n<td>\n<p>\n<span>Number and class of securities originally admitted and the date of admission:</span>\n</p>\n</td>\n<td>\n<p>\n<span>2,300,000 Ordinary Shares of 10p each on 10 July 2012 split as follows:</span>\n</p>\n<p>\n<span>i. 774,850</span>\n</p>\n<p>\n<span>ii. 407,260</span>\n</p>\n<p>\n<span>iii. 1,117,890</span>\n</p>\n<p>\n<span>\n</span></p>\n<p>\n<span>3,700,000 Ordinary Shares of 10p each on 16 March 2016 split as follows:</span>\n</p>\n<p>\n<span>i. 3,000,000</span>\n</p>\n<p>\n<span>ii. 200,000</span>\n</p>\n<p>\n<span>iii. 500,000</span>\n</p>\n<p>\n<span>\n</span></p>\n<p>\n<span>1,750,000 Ordinary Shares of 10p each on 8 December 2016 split as follows:</span>\n</p>\n<p>\n<span>i. 89,296</span>\n</p>\n<p>\n<span>ii. 9,890</span>\n</p>\n<p>\n<span>iii. 468,610</span>\n</p>\n<p>\n<span>iv. nil</span>\n</p>\n<p>\n<span>v. 982,204</span>\n</p>\n<p>\n<span>vi. 200,000</span>\n</p>\n<p>\n<span>\n</span></p>\n</td>\n</tr>\n<tr>\n<td>\n<p>\n<span>Total issued share capital as at the end of this period (including any shares held in Treasury):</span>\n</p>\n</td>\n<td>\n<p>\n<span>59,523,595 ordinary shares</span>\n</p>\n<p>\n<span>\n</span></p>\n<p>\n<span>The Company holds no ordinary shares in Treasury</span>\n</p>\n</td>\n</tr>\n<tr>\n<td>\n<p>\n<span>Contact name and telephone:</span>\n</p>\n</td>\n<td>\n<p>\n<span>Erik E. Miller +1-925-365-0332</span>\n</p>\n</td>\n</tr>\n</tbody>\n</table></div>\n<p>\n<span>\n</span></p>\n<p>\n<span>\n</span></p>\n<p>\n<span>\n</span></p>\n<p>\n<span>For further information, please contact:</span>\n</p>\n<p>\n<span>\n</span></p>\n<div class=\"story-table-container\"><table class=\"story-basic-table\">\n<tbody>\n<tr>\n<td>\n<p>\n<span>WANdisco plc</span>\n</p>\n</td>\n<td>\n<p>\n<span>via FTI Consulting</span>\n</p>\n</td>\n</tr>\n<tr>\n<td>\n<p>\n<span>David Richards, Chief Executive Officer and Chairman</span>\n</p>\n</td>\n<td>\n<p>\n<span>\n</span></p>\n</td>\n</tr>\n<tr>\n<td>\n<p>\n<span>Erik Miller, Chief Financial Officer</span>\n</p>\n</td>\n<td>\n<p>\n<span>\n</span></p>\n</td>\n</tr>\n<tr>\n<td>\n<p>\n<span>Daud Khan, VP Corporate Development</span>\n</p>\n</td>\n<td>\n<p>\n<span>\n</span></p>\n</td>\n</tr>\n<tr>\n<td>\n<p>\n<span>\n</span></p>\n</td>\n<td>\n<p>\n<span>\n</span></p>\n</td>\n</tr>\n<tr>\n<td>\n<p>\n<span>\n</span></p>\n</td>\n<td>\n<p>\n<span>\n</span></p>\n</td>\n</tr>\n<tr>\n<td>\n<p>\n<span>\n</span></p>\n</td>\n<td>\n<p>\n<span>\n</span></p>\n</td>\n</tr>\n<tr>\n<td>\n<p>\n<span>FTI Consulting</span>\n</p>\n</td>\n<td>\n<p>\n<span>+44 (0)20 3727 1137</span>\n</p>\n</td>\n</tr>\n<tr>\n<td>\n<p>\n<span>Matt Dixon / Kwaku Aning / Tom Blundell</span>\n</p>\n<p>\n<span>\n\n</span>\n</p>\n</td>\n<td>\n<p>\n<span>\n</span></p>\n</td>\n</tr>\n<tr>\n<td>\n<p>\n<span>\n<span>Stifel</span>\n</span>\n<span>(Nomad and Broker)</span>\n</p>\n</td>\n<td>\n<p>\n<span>\n<span>+44 (0)20 7</span>\n</span>\n<span>\n<span>710 7600</span>\n</span>\n</p>\n</td>\n</tr>\n<tr>\n<td>\n<p>\n<span>Fred Walsh / Richard Short</span>\n</p>\n<p>\n<span>\n</span></p>\n</td>\n<td>\n<p>\n<span>\n</span></p>\n</td>\n</tr>\n<tr>\n<td>\n<p>\n<span>\n<span>Panmure</span>\n</span>\n<span>(Joint Broker)</span>\n</p>\n</td>\n<td>\n<p>\n<span>+44 (0)20 7886 2500</span>\n</p>\n</td>\n</tr>\n<tr>\n<td>\n<p>\n<span>Erik Anderson / Alina Vaskina</span>\n</p>\n</td>\n<td>\n<p>\n<span>\n</span></p>\n</td>\n</tr>\n<tr>\n<td>\n<p>\n<span>\n</span></p>\n</td>\n<td>\n<p>\n<span>\n</span></p>\n</td>\n</tr>\n</tbody>\n</table></div>\n<p>\n<span>About WANdisco</span>\n</p>\n<p>\n<span>WANdisco is the LiveData company for machine learning and AI. WANdisco solutions enable enterprises to create an environment where data is always available, accurate and protected, creating a strong backbone for their IT infrastructure and a bedrock for running consistent, accurate machine learning applications. With zero downtime and zero data loss, WANdisco Fusion keeps geographically dispersed data at any scale consistent between on-premises and cloud environments allowing businesses to operate seamlessly in a hybrid or multi-cloud environment. WANdisco has over a hundred customers and significant go-to-market partnerships with Microsoft Azure, Amazon Web Services, Google Cloud, Oracle, and others as well as OEM relationships with IBM and Alibaba.</span>\n</p>\n<p>\n<span>\n</span></p>\n<p>\n<span>For more information on WANdisco, visit</span>\n<span>\n<span>\n<a href=\"http://www.wandisco.com/\" data-type=\"url\" class=\"tr-link\" translate=\"no\">www.wandisco.com</a>\n</span>\n</span>\n<span>.</span>\n<span>\n</span></p>\n<p>\n<span>\n</span></p>\n<p>This information is provided by RNS, the news service of the London Stock Exchange. RNS is approved by the Financial Conduct Authority to act as a Primary Information Provider in the United Kingdom. Terms and conditions relating to the use and distribution of this information may apply. For further information, please contact <a href=\"mailto:rns@lseg.com\" data-type=\"email\" translate=\"no\">rns@lseg.com</a> or visit <a href=\"http://www.rns.com/\" data-type=\"url\" class=\"tr-link\" translate=\"no\">www.rns.com</a> .RNS may use your IP address to confirm compliance with the terms and conditions, to analyse how you engage with the information contained in this communication, and to share such analysis on an anonymised basis with others as part of our commercial services. For further information about how RNS and the London Stock Exchange use the personal data you provide us, please see our <a href=\"https://www.lseg.com/privacy-and-cookie-policy\" data-type=\"url\" class=\"tr-link\" translate=\"no\">Privacy Policy</a> .END</p>\n<p>BLRTTBBTMTMMBMB</p>\n</div><p class=\"line-break\"><br/></p><p class=\"tr-copyright\">Copyright (c) 2021 Thomson Reuters Limited.</p></div>"}