{"date": "2021-11-30 10:20:38+00:00", "ticker": "AMZN", "mrkt_info": {"open": 3561.57, "close": 3443.72}, "html": "<div class=\"storyContent\" lang=\"en\"><style type=\"text/css\">.storyContent * {border-color:inherit !important;outline-color:inherit !important;}</style><div id=\"notext_disclaimer\">\n                <p>\n        The text version of this document is not available. You can access the original document <a href=\"http://www.wftucentral.org/the-wftu-took-part-in-the-meeting-of-support-amazon-workers-on-november-29-2021-in-solidarity-with-amazon-and-other-workers/\" data-type=\"url\" class=\"tr-link\" translate=\"no\">here</a>.\n      </p>\n              </div>\n              <div id=\"public_attachments\">\n                <p>\n                  <strong>Attachments</strong>\n                </p>\n                <ul class=\"bulleted-list arrowlist\">\n                  <li>\n                    <a href=\"http://www.wftucentral.org/the-wftu-took-part-in-the-meeting-of-support-amazon-workers-on-november-29-2021-in-solidarity-with-amazon-and-other-workers/\" data-type=\"url\" class=\"tr-link\" translate=\"no\">Original document</a>\n                  </li>\n                </ul>\n              </div>\n              <div id=\"public_disclaimer\">\n                <p>\n                  <strong>Disclaimer</strong>\n                </p>\n                <p>\n                  <strong>WFTU - World Federation of Trade Unions</strong> published this content on <strong>30 November 2021</strong> and is solely responsible for the information contained therein. Distributed by Public, unedited and unaltered, on <strong>30 November 2021 10:20:38 UTC</strong></p>\n              </div><p class=\"line-break\"><br/></p><p class=\"tr-copyright\">(C) Copyright 2021 - WFTU - World Federation of Trade Unions</p><p class=\"line-break\"><br/></p><p class=\"tr-slugline\">Keywords: WFTU---World-Federation-of-Trade-Unions</p></div>"}