{"date": "2020-12-11 10:23:32+00:00", "ticker": "AVV", "mrkt_info": {"open": 3284.0, "close": 3195.0}, "html": "<div class=\"storyContent\" lang=\"en\"><style type=\"text/css\">.storyContent * {border-color:inherit !important;outline-color:inherit !important;}.storyContent sup{font-size:80%;}.storyContent h1{margin-top:12.0pt;margin-right:0cm;margin-bottom:3.0pt;margin-left:0cm;font-size:16.0pt;font-weight:bold;}.storyContent h2{margin-top:12.0pt;margin-right:0cm;margin-bottom:3.0pt;margin-left:0cm;font-size:14.0pt;font-weight:bold;}.storyContent h3{margin-top:12.0pt;margin-right:0cm;margin-bottom:3.0pt;margin-left:0cm;text-indent:-14.15pt;font-size:13.0pt;font-weight:bold;}.storyContent h4{margin-top:12.0pt;margin-right:0cm;margin-bottom:3.0pt;margin-left:14.85pt;text-indent:-43.2pt;font-size:14.0pt;font-weight:bold;}.storyContent h5{margin-top:12.0pt;margin-right:0cm;margin-bottom:3.0pt;margin-left:22.05pt;text-indent:-50.4pt;font-size:13.0pt;font-weight:bold;}.storyContent h6{margin-top:12.0pt;margin-right:0cm;margin-bottom:3.0pt;margin-left:29.25pt;text-indent:-57.6pt;font-size:11.0pt;font-weight:bold;}.storyContent p{margin-right:0cm;margin-left:0cm;font-size:12.0pt;}.storyContent ol{margin-bottom:0cm;}.storyContent ul{margin-bottom:0cm;}.storyContent .bx{margin:127.6pt 62.35pt 68.05pt 62.35pt;}.storyContent p.ix{margin:0cm;margin-bottom:.0001pt;font-size:11.0pt;margin-left:-35.45pt;}.storyContent span.iv{font-size:14.0pt;}.storyContent span.iu{font-size:14.0pt;}.storyContent p.iy{margin:0cm;margin-bottom:.0001pt;font-size:11.0pt;font-weight:bold;margin-left:-35.45pt;}.storyContent table.iz{margin-left:-36.0pt;border-collapse:collapse;border:none;border-color:inherit;}.storyContent tr.ik{height:21.1pt;}.storyContent td.il{width:520.2pt;border:solid windowtext 1.0pt;padding:0cm 5.4pt 0cm 5.4pt;height:21.1pt;border-color:inherit;}.storyContent p.ja{margin:0cm;margin-bottom:.0001pt;font-size:11.0pt;text-autospace:none;}.storyContent span.iq{font-size:12.0pt;}.storyContent span.ip{text-decoration:underline;text-decoration-color:inherit;}.storyContent span.in{font-size:8.0pt;}.storyContent tr.ig{height:12.1pt;}.storyContent td.ih{width:520.2pt;border:none;border-bottom:solid windowtext 1.0pt;padding:0cm 5.4pt 0cm 5.4pt;height:12.1pt;border-color:inherit;}.storyContent p.jb{margin:0cm;margin-bottom:.0001pt;font-size:11.0pt;text-align:right;}.storyContent span.ij{font-size:10.0pt;}.storyContent tr.ia{height:43.85pt;}.storyContent td.id{width:259.1pt;border:solid windowtext 1.0pt;border-top:none;padding:0cm 5.4pt 0cm 5.4pt;height:43.85pt;border-color:inherit;}.storyContent p.a,.storyContent li.a,.storyContent div.a{margin:0cm;margin-bottom:.0001pt;font-size:11.0pt;}.storyContent span.ie{font-size:8.0pt;}.storyContent span.jc{vertical-align:super;}.storyContent td.ib{width:250.3pt;border-top:none;border-left:none;border-bottom:solid windowtext 1.0pt;border-right:solid windowtext 1.0pt;padding:0cm 5.4pt 0cm 5.4pt;height:43.85pt;}.storyContent p.jd{margin:0cm;margin-bottom:.0001pt;font-size:11.0pt;text-align:center;}.storyContent tr.hw{height:21.65pt;}.storyContent td.hx{width:520.2pt;border:solid windowtext 1.0pt;border-top:none;padding:0cm 5.4pt 0cm 5.4pt;height:21.65pt;border-color:inherit;}.storyContent tr.hs{height:19.85pt;}.storyContent td.hu{width:485.9pt;border:solid windowtext 1.0pt;border-top:none;padding:0cm 5.4pt 0cm 5.4pt;height:19.85pt;border-color:inherit;}.storyContent span.hv{font-size:10.5pt;}.storyContent td.ht{width:23.5pt;border-top:none;border-left:none;border-bottom:solid windowtext 1.0pt;border-right:solid windowtext 1.0pt;padding:0cm 5.4pt 0cm 5.4pt;height:19.85pt;}.storyContent tr.hq{height:28.9pt;}.storyContent td.hr{width:520.2pt;border:solid windowtext 1.0pt;border-top:none;padding:0cm 5.4pt 0cm 5.4pt;height:28.9pt;border-color:inherit;}.storyContent tr.hm{height:22.0pt;}.storyContent td.ho{width:485.9pt;border:solid windowtext 1.0pt;border-top:none;padding:0cm 5.4pt 0cm 5.4pt;height:22.0pt;border-color:inherit;}.storyContent span.hp{font-size:10.5pt;}.storyContent td.hn{width:23.5pt;border-top:none;border-left:none;border-bottom:solid windowtext 1.0pt;border-right:solid windowtext 1.0pt;padding:0cm 5.4pt 0cm 5.4pt;height:22.0pt;}.storyContent tr.hk{height:23.4pt;}.storyContent td.hl{width:520.2pt;border-top:none;border-left:solid windowtext 1.0pt;border-bottom:none;border-right:solid windowtext 1.0pt;padding:0cm 5.4pt 0cm 5.4pt;height:23.4pt;}.storyContent tr.hh{height:19.5pt;}.storyContent td.hj{width:259.1pt;border:solid windowtext 1.0pt;border-bottom:none;padding:0cm 5.4pt 0cm 5.4pt;height:19.5pt;border-color:inherit;}.storyContent td.hi{width:250.3pt;border-top:solid windowtext 1.0pt;border-left:none;border-bottom:none;border-right:solid windowtext 1.0pt;padding:0cm 5.4pt 0cm 5.4pt;height:19.5pt;}.storyContent tr.he{height:24.45pt;}.storyContent td.hf{width:520.2pt;border:solid windowtext 1.0pt;padding:0cm 5.4pt 0cm 5.4pt;height:24.45pt;border-color:inherit;}.storyContent span.hg{font-size:8.0pt;}.storyContent tr.hb{height:24.15pt;}.storyContent td.hd{width:259.1pt;border:solid windowtext 1.0pt;border-top:none;padding:0cm 5.4pt 0cm 5.4pt;height:24.15pt;border-color:inherit;}.storyContent td.hc{width:250.3pt;border-top:none;border-left:none;border-bottom:solid windowtext 1.0pt;border-right:solid windowtext 1.0pt;padding:0cm 5.4pt 0cm 5.4pt;height:24.15pt;}.storyContent tr.gy{height:26.85pt;}.storyContent td.ha{width:259.1pt;border:solid windowtext 1.0pt;border-top:none;padding:0cm 5.4pt 0cm 5.4pt;height:26.85pt;border-color:inherit;}.storyContent td.gz{width:250.3pt;border-top:none;border-left:none;border-bottom:solid windowtext 1.0pt;border-right:solid windowtext 1.0pt;padding:0cm 5.4pt 0cm 5.4pt;height:26.85pt;}.storyContent tr.gv{height:33.45pt;}.storyContent td.gx{width:259.1pt;border:solid windowtext 1.0pt;border-top:none;padding:0cm 5.4pt 0cm 5.4pt;height:33.45pt;border-color:inherit;}.storyContent td.gw{width:250.3pt;border-top:none;border-left:none;border-bottom:solid windowtext 1.0pt;border-right:solid windowtext 1.0pt;padding:0cm 5.4pt 0cm 5.4pt;height:33.45pt;}.storyContent tr.gq{height:26.75pt;}.storyContent td.gs{width:259.1pt;border:solid windowtext 1.0pt;border-top:none;padding:0cm 5.4pt 0cm 5.4pt;height:26.75pt;border-color:inherit;}.storyContent p.je{margin:0cm;margin-bottom:.0001pt;font-size:11.0pt;font-weight:bold;}.storyContent td.gr{width:250.3pt;border-top:none;border-left:none;border-bottom:solid windowtext 1.0pt;border-right:solid windowtext 1.0pt;padding:0cm 5.4pt 0cm 5.4pt;height:26.75pt;}.storyContent tr.go{height:27.75pt;}.storyContent td.gp{width:520.2pt;border:solid windowtext 1.0pt;border-top:none;padding:0cm 5.4pt 0cm 5.4pt;height:27.75pt;border-color:inherit;}.storyContent td.gn{width:95.4pt;border:solid windowtext 1.0pt;border-top:none;padding:0cm 5.4pt 0cm 5.4pt;height:27.75pt;border-color:inherit;}.storyContent td.gm{width:95.4pt;border-top:none;border-left:none;border-bottom:solid windowtext 1.0pt;border-right:solid windowtext 1.0pt;padding:0cm 5.4pt 0cm 5.4pt;height:27.75pt;}.storyContent td.gl{width:104.85pt;border-top:none;border-left:none;border-bottom:solid windowtext 1.0pt;border-right:solid windowtext 1.0pt;padding:0cm 5.4pt 0cm 5.4pt;height:27.75pt;}.storyContent td.gk{width:95.5pt;border-top:none;border-left:none;border-bottom:solid windowtext 1.0pt;border-right:solid windowtext 1.0pt;padding:0cm 5.4pt 0cm 5.4pt;height:27.75pt;}.storyContent td.gj{width:85.85pt;border-top:none;border-left:none;border-bottom:solid windowtext 1.0pt;border-right:solid windowtext 1.0pt;padding:0cm 5.4pt 0cm 5.4pt;height:27.75pt;}.storyContent tr.gd{height:42.4pt;}.storyContent td.gi{width:95.4pt;border:solid windowtext 1.0pt;border-top:none;padding:0cm 5.4pt 0cm 5.4pt;height:42.4pt;border-color:inherit;}.storyContent td.gh{width:95.4pt;border-top:none;border-left:none;border-bottom:solid windowtext 1.0pt;border-right:solid windowtext 1.0pt;padding:0cm 5.4pt 0cm 5.4pt;height:42.4pt;}.storyContent td.gg{width:104.85pt;border-top:none;border-left:none;border-bottom:solid windowtext 1.0pt;border-right:solid windowtext 1.0pt;padding:0cm 5.4pt 0cm 5.4pt;height:42.4pt;}.storyContent td.gf{width:95.5pt;border-top:none;border-left:none;border-bottom:solid windowtext 1.0pt;border-right:solid windowtext 1.0pt;padding:0cm 5.4pt 0cm 5.4pt;height:42.4pt;}.storyContent td.ge{width:85.85pt;border-top:none;border-left:none;border-bottom:solid windowtext 1.0pt;border-right:solid windowtext 1.0pt;padding:0cm 5.4pt 0cm 5.4pt;height:42.4pt;}.storyContent tr.gb{height:16.3pt;}.storyContent td.gc{width:520.2pt;border:solid windowtext 1.0pt;border-top:none;padding:0cm 5.4pt 0cm 5.4pt;height:16.3pt;border-color:inherit;}.storyContent tr.fz{height:22.9pt;}.storyContent td.ga{width:520.2pt;border:solid windowtext 1.0pt;border-top:none;padding:0cm 5.4pt 0cm 5.4pt;height:22.9pt;border-color:inherit;}.storyContent tr.fv{height:19.3pt;}.storyContent td.fy{width:99.65pt;border:solid windowtext 1.0pt;border-top:none;padding:0cm 5.4pt 0cm 5.4pt;height:19.3pt;border-color:inherit;}.storyContent td.fx{width:191.95pt;border:none;padding:0cm 5.4pt 0cm 5.4pt;height:19.3pt;border-color:inherit;}.storyContent td.fw{width:207.0pt;border-top:none;border-left:solid windowtext 1.0pt;border-bottom:none;border-right:solid windowtext 1.0pt;padding:0cm 5.4pt 0cm 5.4pt;height:19.3pt;}.storyContent tr.fp{height:18.7pt;}.storyContent td.ft{width:90.35pt;border:solid windowtext 1.0pt;border-left:none;padding:0cm 5.4pt 0cm 5.4pt;height:18.7pt;border-color:inherit;}.storyContent p.jf{margin:0cm;margin-bottom:.0001pt;font-size:11.0pt;font-weight:bold;text-align:center;}.storyContent td.fs{width:90.8pt;border-top:none;border-left:none;border-bottom:solid windowtext 1.0pt;border-right:solid windowtext 1.0pt;padding:0cm 5.4pt 0cm 5.4pt;height:18.7pt;}.storyContent td.fr{width:105.8pt;border:solid windowtext 1.0pt;border-left:none;padding:0cm 5.4pt 0cm 5.4pt;height:18.7pt;border-color:inherit;}.storyContent td.fq{width:90.4pt;border:solid windowtext 1.0pt;border-left:none;padding:0cm 5.4pt 0cm 5.4pt;height:18.7pt;border-color:inherit;}.storyContent tr.fi{height:23.5pt;}.storyContent td.fn{width:99.65pt;border:solid windowtext 1.0pt;border-top:none;padding:0cm 5.4pt 0cm 5.4pt;height:23.5pt;border-color:inherit;}.storyContent span.fo{font-size:12.0pt;}.storyContent td.fm{width:90.35pt;border-top:none;border-left:none;border-bottom:solid windowtext 1.0pt;border-right:solid windowtext 1.0pt;padding:0cm 5.4pt 0cm 5.4pt;height:23.5pt;}.storyContent td.fl{width:90.8pt;border-top:none;border-left:none;border-bottom:solid windowtext 1.0pt;border-right:solid windowtext 1.0pt;padding:0cm 5.4pt 0cm 5.4pt;height:23.5pt;}.storyContent td.fk{width:105.8pt;border-top:none;border-left:none;border-bottom:solid windowtext 1.0pt;border-right:solid windowtext 1.0pt;padding:0cm 5.4pt 0cm 5.4pt;height:23.5pt;}.storyContent td.fj{width:90.4pt;border-top:none;border-left:none;border-bottom:solid windowtext 1.0pt;border-right:solid windowtext 1.0pt;padding:0cm 5.4pt 0cm 5.4pt;height:23.5pt;}.storyContent td.fh{width:191.95pt;border-top:none;border-left:none;border-bottom:solid windowtext 1.0pt;border-right:solid windowtext 1.0pt;padding:0cm 5.4pt 0cm 5.4pt;height:23.5pt;}.storyContent td.fg{width:207.0pt;border-top:none;border-left:none;border-bottom:solid windowtext 1.0pt;border-right:solid windowtext 1.0pt;padding:0cm 5.4pt 0cm 5.4pt;height:23.5pt;}.storyContent tr.fe{height:10.9pt;}.storyContent td.ff{width:520.2pt;border:none;padding:0cm 5.4pt 0cm 5.4pt;height:10.9pt;border-color:inherit;}.storyContent tr.fc{height:26.5pt;}.storyContent td.fd{width:520.2pt;border:solid windowtext 1.0pt;padding:0cm 5.4pt 0cm 5.4pt;height:26.5pt;border-color:inherit;}.storyContent td.fb{width:99.65pt;border:solid windowtext 1.0pt;border-top:none;padding:0cm 5.4pt 0cm 5.4pt;border-color:inherit;}.storyContent td.fa{width:51.1pt;border-top:none;border-left:none;border-bottom:solid windowtext 1.0pt;border-right:solid windowtext 1.0pt;padding:0cm 5.4pt 0cm 5.4pt;}.storyContent td.ey{width:117.1pt;border-top:none;border-left:none;border-bottom:solid windowtext 1.0pt;border-right:solid windowtext 1.0pt;padding:0cm 5.4pt 0cm 5.4pt;}.storyContent span.ez{font-size:8.0pt;}.storyContent td.ex{width:118.75pt;border-top:none;border-left:none;border-bottom:solid windowtext 1.0pt;border-right:solid windowtext 1.0pt;padding:0cm 5.4pt 0cm 5.4pt;}.storyContent td.ew{width:90.4pt;border-top:none;border-left:none;border-bottom:solid windowtext 1.0pt;border-right:solid windowtext 1.0pt;padding:0cm 5.4pt 0cm 5.4pt;}.storyContent tr.eq{height:24.05pt;}.storyContent td.ev{width:99.65pt;border:solid windowtext 1.0pt;border-top:none;padding:0cm 5.4pt 0cm 5.4pt;height:24.05pt;border-color:inherit;}.storyContent td.eu{width:51.1pt;border-top:none;border-left:none;border-bottom:solid windowtext 1.0pt;border-right:solid windowtext 1.0pt;padding:0cm 5.4pt 0cm 5.4pt;height:24.05pt;}.storyContent td.et{width:117.1pt;border-top:none;border-left:none;border-bottom:solid windowtext 1.0pt;border-right:solid windowtext 1.0pt;padding:0cm 5.4pt 0cm 5.4pt;height:24.05pt;}.storyContent td.es{width:118.75pt;border-top:none;border-left:none;border-bottom:solid windowtext 1.0pt;border-right:solid windowtext 1.0pt;padding:0cm 5.4pt 0cm 5.4pt;height:24.05pt;}.storyContent td.er{width:90.4pt;border-top:none;border-left:none;border-bottom:solid windowtext 1.0pt;border-right:solid windowtext 1.0pt;padding:0cm 5.4pt 0cm 5.4pt;height:24.05pt;}.storyContent td.ep{width:99.65pt;border:none;padding:0cm 5.4pt 0cm 5.4pt;height:24.05pt;border-color:inherit;}.storyContent td.eo{width:51.1pt;border:none;border-right:solid windowtext 1.0pt;padding:0cm 5.4pt 0cm 5.4pt;height:24.05pt;border-color:inherit;}.storyContent tr.em{height:20.4pt;}.storyContent td.en{width:520.2pt;border:solid windowtext 1.0pt;padding:0cm 5.4pt 0cm 5.4pt;height:20.4pt;border-color:inherit;}.storyContent td.el{width:79.1pt;border:solid windowtext 1.0pt;border-top:none;padding:0cm 5.4pt 0cm 5.4pt;border-color:inherit;}.storyContent td.ek{width:71.65pt;border-top:none;border-left:none;border-bottom:solid windowtext 1.0pt;border-right:solid windowtext 1.0pt;padding:0cm 5.4pt 0cm 5.4pt;}.storyContent td.ej{width:78.5pt;border-top:none;border-left:none;border-bottom:solid windowtext 1.0pt;border-right:solid windowtext 1.0pt;padding:0cm 5.4pt 0cm 5.4pt;}.storyContent td.ei{width:77.75pt;border-top:none;border-left:none;border-bottom:solid windowtext 1.0pt;border-right:solid windowtext 1.0pt;padding:0cm 5.4pt 0cm 5.4pt;}.storyContent td.eh{width:68.8pt;border:none;border-bottom:solid windowtext 1.0pt;padding:0cm 5.4pt 0cm 5.4pt;border-color:inherit;}.storyContent td.eg{width:90.4pt;border:solid windowtext 1.0pt;border-top:none;padding:0cm 5.4pt 0cm 5.4pt;border-color:inherit;}.storyContent td.ef{width:79.1pt;border:solid windowtext 1.0pt;border-top:none;padding:0cm 5.4pt 0cm 5.4pt;height:24.05pt;border-color:inherit;}.storyContent td.ee{width:71.65pt;border-top:none;border-left:none;border-bottom:solid windowtext 1.0pt;border-right:solid windowtext 1.0pt;padding:0cm 5.4pt 0cm 5.4pt;height:24.05pt;}.storyContent td.ed{width:78.5pt;border-top:none;border-left:none;border-bottom:solid windowtext 1.0pt;border-right:solid windowtext 1.0pt;padding:0cm 5.4pt 0cm 5.4pt;height:24.05pt;}.storyContent td.ec{width:77.75pt;border-top:none;border-left:none;border-bottom:solid windowtext 1.0pt;border-right:solid windowtext 1.0pt;padding:0cm 5.4pt 0cm 5.4pt;height:24.05pt;}.storyContent td.eb{width:68.8pt;border:none;border-bottom:solid windowtext 1.0pt;padding:0cm 5.4pt 0cm 5.4pt;height:24.05pt;border-color:inherit;}.storyContent td.ea{width:90.4pt;border:solid windowtext 1.0pt;border-top:none;padding:0cm 5.4pt 0cm 5.4pt;height:24.05pt;border-color:inherit;}.storyContent td.dz{width:79.1pt;border:solid windowtext 1.0pt;border-top:none;padding:0cm 5.4pt 0cm 5.4pt;height:24.05pt;border-color:inherit;}.storyContent td.dy{width:71.65pt;border-top:none;border-left:none;border-bottom:solid windowtext 1.0pt;border-right:solid windowtext 1.0pt;padding:0cm 5.4pt 0cm 5.4pt;height:24.05pt;}.storyContent td.dx{width:78.5pt;border-top:none;border-left:none;border-bottom:solid windowtext 1.0pt;border-right:solid windowtext 1.0pt;padding:0cm 5.4pt 0cm 5.4pt;height:24.05pt;}.storyContent td.dw{width:77.75pt;border-top:none;border-left:none;border-bottom:solid windowtext 1.0pt;border-right:solid windowtext 1.0pt;padding:0cm 5.4pt 0cm 5.4pt;height:24.05pt;}.storyContent td.dv{width:79.1pt;border:none;padding:0cm 5.4pt 0cm 5.4pt;height:24.05pt;border-color:inherit;}.storyContent td.du{width:71.65pt;border:none;padding:0cm 5.4pt 0cm 5.4pt;height:24.05pt;border-color:inherit;}.storyContent td.dt{width:78.5pt;border:none;border-right:solid windowtext 1.0pt;padding:0cm 5.4pt 0cm 5.4pt;height:24.05pt;border-color:inherit;}.storyContent td.ds{border:none;border-color:inherit;}.storyContent tr.dp{height:29.75pt;}.storyContent td.dq{width:524.85pt;border:solid windowtext 1.0pt;border-bottom:none;padding:0cm 5.4pt 0cm 5.4pt;height:29.75pt;border-color:inherit;}.storyContent tr.dm{height:31.7pt;}.storyContent td.do{width:490.55pt;border:solid windowtext 1.0pt;border-bottom:none;padding:0cm 5.4pt 0cm 5.4pt;height:31.7pt;border-color:inherit;}.storyContent td.dn{width:23.5pt;border-top:solid windowtext 1.0pt;border-left:none;border-bottom:none;border-right:solid windowtext 1.0pt;padding:0cm 5.4pt 0cm 5.4pt;height:31.7pt;}.storyContent tr.dg{height:38.5pt;}.storyContent td.di{width:490.55pt;border:solid windowtext 1.0pt;padding:0cm 5.4pt 0cm 5.4pt;height:38.5pt;border-color:inherit;}.storyContent span.dl{font-size:10.0pt;text-decoration:underline;text-decoration-color:inherit;}.storyContent span.dk{font-size:10.0pt;}.storyContent span.dj{font-size:10.0pt;}.storyContent td.dh{width:23.5pt;border:solid windowtext 1.0pt;border-left:none;padding:0cm 5.4pt 0cm 5.4pt;height:38.5pt;border-color:inherit;}.storyContent tr.db{height:57.45pt;}.storyContent td.df{width:125.9pt;border:solid windowtext 1.0pt;border-top:none;padding:0cm 5.4pt 0cm 5.4pt;height:57.45pt;border-color:inherit;}.storyContent td.de{width:121.95pt;border-top:none;border-left:none;border-bottom:solid windowtext 1.0pt;border-right:solid windowtext 1.0pt;padding:0cm 5.4pt 0cm 5.4pt;height:57.45pt;}.storyContent td.dd{width:121.95pt;border-top:none;border-left:none;border-bottom:solid windowtext 1.0pt;border-right:solid windowtext 1.0pt;padding:0cm 5.4pt 0cm 5.4pt;height:57.45pt;}.storyContent td.dc{border:none;padding:0cm 0cm 0cm 0cm;border-color:inherit;}.storyContent td.da{width:125.9pt;border:solid windowtext 1.0pt;border-top:none;padding:0cm 5.4pt 0cm 5.4pt;height:22.0pt;border-color:inherit;}.storyContent td.cz{width:121.95pt;border-top:none;border-left:none;border-bottom:solid windowtext 1.0pt;border-right:solid windowtext 1.0pt;padding:0cm 5.4pt 0cm 5.4pt;height:22.0pt;}.storyContent td.cy{width:121.95pt;border-top:none;border-left:none;border-bottom:solid windowtext 1.0pt;border-right:solid windowtext 1.0pt;padding:0cm 5.4pt 0cm 5.4pt;height:22.0pt;}.storyContent td.cx{border:none;border-bottom:solid windowtext 1.0pt;border-color:inherit;}.storyContent tr.cv{height:35.5pt;}.storyContent td.cw{width:524.85pt;border:none;border-bottom:solid windowtext 1.0pt;padding:0cm 5.4pt 0cm 5.4pt;height:35.5pt;border-color:inherit;}.storyContent tr.cs{height:20.7pt;}.storyContent td.ct{width:524.85pt;border:solid windowtext 1.0pt;border-top:none;padding:0cm 5.4pt 0cm 5.4pt;height:20.7pt;border-color:inherit;}.storyContent tr.cp{height:20.3pt;}.storyContent td.cr{width:259.35pt;border:solid windowtext 1.0pt;border-top:none;padding:0cm 5.4pt 0cm 5.4pt;height:20.3pt;border-color:inherit;}.storyContent td.cq{width:254.7pt;border-top:none;border-left:none;border-bottom:solid windowtext 1.0pt;border-right:solid windowtext 1.0pt;padding:0cm 5.4pt 0cm 5.4pt;height:20.3pt;}.storyContent td.co{width:259.35pt;border:solid windowtext 1.0pt;border-top:none;padding:0cm 5.4pt 0cm 5.4pt;height:27.75pt;border-color:inherit;}.storyContent td.cn{width:254.7pt;border-top:none;border-left:none;border-bottom:solid windowtext 1.0pt;border-right:solid windowtext 1.0pt;padding:0cm 5.4pt 0cm 5.4pt;height:27.75pt;}.storyContent tr.ck{height:28.1pt;}.storyContent td.cm{width:259.35pt;border:solid windowtext 1.0pt;border-top:none;padding:0cm 5.4pt 0cm 5.4pt;height:28.1pt;border-color:inherit;}.storyContent td.cl{width:254.7pt;border-top:none;border-left:none;border-bottom:solid windowtext 1.0pt;border-right:solid windowtext 1.0pt;padding:0cm 5.4pt 0cm 5.4pt;height:28.1pt;}.storyContent td.cj{width:524.85pt;border:none;padding:0cm 5.4pt 0cm 5.4pt;height:26.5pt;border-color:inherit;}.storyContent tr.ch{height:21.85pt;}.storyContent td.ci{width:524.85pt;border:solid windowtext 1.0pt;padding:0cm 5.4pt 0cm 5.4pt;height:21.85pt;border-color:inherit;}.storyContent tr.cf{height:47.5pt;}.storyContent td.cg{width:524.85pt;border:solid windowtext 1.0pt;border-top:none;padding:0cm 5.4pt 0cm 5.4pt;height:47.5pt;border-color:inherit;}.storyContent table.jg{width:531.6pt;margin-left:-35.45pt;border-collapse:collapse;border:none;border-color:inherit;}.storyContent tr.cc{height:23.75pt;}.storyContent td.ce{width:109.7pt;border:solid windowtext 1.0pt;padding:0cm 5.4pt 0cm 5.4pt;height:23.75pt;border-color:inherit;}.storyContent td.cd{width:400.3pt;border:solid windowtext 1.0pt;border-left:none;padding:0cm 5.4pt 0cm 5.4pt;height:23.75pt;border-color:inherit;}.storyContent tr.bz{height:21.25pt;}.storyContent td.cb{width:109.7pt;border:solid windowtext 1.0pt;border-top:none;padding:0cm 5.4pt 0cm 5.4pt;height:21.25pt;border-color:inherit;}.storyContent td.ca{width:400.3pt;border-top:none;border-left:none;border-bottom:solid windowtext 1.0pt;border-right:solid windowtext 1.0pt;padding:0cm 5.4pt 0cm 5.4pt;height:21.25pt;}</style><div class=\"tr-image\"><div class=\"tr-image-components\"></div></div><div style=\"text-align:left;font-size:10pt\"><div>RNS Number : 3793I</div>  <div>AVEVA Group PLC</div>  <div>11 December 2020</div>  <div>\u00a0</div></div>\n<div class=\"bx\">\n<p class=\"ix\"><span style=\"font-weight:bold\"><span class=\"iv\">TR-1: S</span></span><span style=\"font-weight:bold\"><span class=\"iu\">tandard form for notification of major holdings</span></span></p>\n<p class=\"iy\"><span class=\"iv\">\u00a0</span></p>\n<div class=\"story-table-container\"><table cellpadding=\"0\" cellspacing=\"0\" class=\"iz\" style=\"width:708\">\n<tr class=\"ik\">\n<td class=\"il\" colspan=\"15\" style=\"width:694\">\n<p class=\"ja\"><span style=\"font-weight:bold\"><span class=\"ir\">NOTIFICATION OF MAJOR HOLDINGS</span></span><span style=\"font-weight:bold\"><span class=\"iq\"> </span></span><span class=\"io\">(to be sent to the relevant issuer <span class=\"ip\">and</span> to the FCA in Microsoft Word format if possible)</span><sup><span class=\"in\">i</span></sup></p>\n</td>\n</tr>\n<tr class=\"ig\">\n<td class=\"ih\" colspan=\"15\" style=\"width:694\">\n<p class=\"jb\"><span class=\"ij\"><br/></span></p>\n</td>\n</tr>\n<tr class=\"ia\">\n<td class=\"id\" colspan=\"8\" style=\"width:345\">\n<p class=\"a\"><span style=\"font-weight:bold\"><span class=\"if\">1a. Identity of the issuer or the underlying issuer of existing shares to which voting rights are attached</span></span><sup><span class=\"ie\">ii</span></sup><span style=\"font-weight:bold\"><span class=\"ir\">:</span></span><span class=\"jc\"> </span></p>\n</td>\n<td class=\"ib\" colspan=\"7\" style=\"width:334\">\n<p class=\"jd\"><span class=\"if\">AVEVA Group Plc</span></p>\n</td>\n</tr>\n<tr class=\"hw\">\n<td class=\"hx\" colspan=\"15\" style=\"width:694\">\n<p class=\"a\"><span style=\"font-weight:bold\"><span class=\"hz\">1b. Please indicate if the issuer is a non-UK issuer \u00a0</span></span><span class=\"hy\">(please mark with an \"X\" if appropriate)</span></p>\n</td>\n</tr>\n<tr class=\"hs\">\n<td class=\"hu\" colspan=\"14\" style=\"width:648\">\n<p class=\"a\"><span class=\"hv\">Non-UK issuer</span></p>\n</td>\n<td class=\"ht\" style=\"width:31\">\n<p class=\"jd\"><span class=\"hy\"><br/></span></p>\n</td>\n</tr>\n<tr class=\"hq\">\n<td class=\"hr\" colspan=\"15\" style=\"width:694\">\n<p class=\"a\"><span style=\"font-weight:bold\"><span class=\"if\">2. Reason for the notification </span></span><span class=\"if\">(please mark the appropriate box or boxes with an \"X\")</span></p>\n</td>\n</tr>\n<tr class=\"hm\">\n<td class=\"ho\" colspan=\"14\" style=\"width:648\">\n<p class=\"a\"><span class=\"hp\">An acquisition or disposal of voting rights</span></p>\n</td>\n<td class=\"hn\" style=\"width:31\">\n<p class=\"jd\"><span class=\"if\">X</span></p>\n</td>\n</tr>\n<tr class=\"hm\">\n<td class=\"ho\" colspan=\"14\" style=\"width:648\">\n<p class=\"a\"><span class=\"hp\">An acquisition or disposal of financial instruments</span></p>\n</td>\n<td class=\"hn\" style=\"width:31\">\n<p class=\"jd\"><span class=\"if\"><br/></span></p>\n</td>\n</tr>\n<tr class=\"hm\">\n<td class=\"ho\" colspan=\"14\" style=\"width:648\">\n<p class=\"a\"><span class=\"hp\">An event changing the breakdown of voting rights</span></p>\n</td>\n<td class=\"hn\" style=\"width:31\">\n<p class=\"jd\"><span class=\"if\"><br/></span></p>\n</td>\n</tr>\n<tr class=\"hm\">\n<td class=\"ho\" colspan=\"14\" style=\"width:648\">\n<p class=\"a\"><span class=\"hp\">Other (please specify)<sup>iii</sup>:</span></p>\n</td>\n<td class=\"hn\" style=\"width:31\">\n<p class=\"jd\"><span class=\"if\"><br/></span></p>\n</td>\n</tr>\n<tr class=\"hk\">\n<td class=\"hl\" colspan=\"15\" style=\"width:694\">\n<p class=\"a\"><span style=\"font-weight:bold\"><span class=\"if\">3. Details of person subject to the notification obligation</span></span><sup><span class=\"in\">iv</span></sup></p>\n</td>\n</tr>\n<tr class=\"hh\">\n<td class=\"hj\" colspan=\"8\" style=\"width:345\">\n<p class=\"a\"><span class=\"hp\">Name</span></p>\n</td>\n<td class=\"hi\" colspan=\"7\" style=\"width:334\">\n<p class=\"a\"><span class=\"if\">Schneider Electric SE</span></p>\n</td>\n</tr>\n<tr class=\"hh\">\n<td class=\"hj\" colspan=\"8\" style=\"width:345\">\n<p class=\"a\"><span class=\"hp\">City and country of registered office (if applicable)</span></p>\n</td>\n<td class=\"hi\" colspan=\"7\" style=\"width:334\">\n<p class=\"a\"><span class=\"if\">Rueil-Malmaison, France</span></p>\n</td>\n</tr>\n<tr class=\"he\">\n<td class=\"hf\" colspan=\"15\" style=\"width:694\">\n<p class=\"a\"><span style=\"font-weight:bold\"><span class=\"if\">4. Full name of shareholder(s)</span></span><span class=\"if\"> (if different from 3.)</span><sup><span class=\"hg\">v</span></sup></p>\n</td>\n</tr>\n<tr class=\"hb\">\n<td class=\"hd\" colspan=\"8\" style=\"width:345\">\n<p class=\"a\"><span class=\"hp\">Name</span></p>\n</td>\n<td class=\"hc\" colspan=\"7\" style=\"width:334\">\n<p class=\"a\"><span class=\"if\">SAMOS Acquisition Company Limited</span></p>\n</td>\n</tr>\n<tr class=\"gy\">\n<td class=\"ha\" colspan=\"8\" style=\"width:345\">\n<p class=\"a\"><span class=\"hp\">City and country of registered office (if applicable)</span></p>\n</td>\n<td class=\"gz\" colspan=\"7\" style=\"width:334\">\n<p class=\"a\"><span class=\"if\">Telford - UK </span></p>\n</td>\n</tr>\n<tr class=\"gv\">\n<td class=\"gx\" colspan=\"8\" style=\"width:345\">\n<p class=\"a\"><span style=\"font-weight:bold\"><span class=\"if\">5. Date on which the threshold was crossed or reached</span></span><sup><span class=\"in\">vi</span></sup><span style=\"font-weight:bold\"><span class=\"if\">:</span></span></p>\n</td>\n<td class=\"gw\" colspan=\"7\" style=\"width:334\">\n<p class=\"a\"><span class=\"if\">December 10, 2020</span></p>\n</td>\n</tr>\n<tr class=\"gq\">\n<td class=\"gs\" colspan=\"8\" style=\"width:345\">\n<p class=\"je\"><span class=\"if\">6. <span class=\"gu\">Date on which issuer notified (DD/MM/YYYY):</span></span></p>\n</td>\n<td class=\"gr\" colspan=\"7\" style=\"width:334\">\n<p class=\"a\"><span class=\"if\">December 10, 2020</span></p>\n</td>\n</tr>\n<tr class=\"go\">\n<td class=\"gp\" colspan=\"15\" style=\"width:694\">\n<p class=\"je\"><span class=\"if\">7. Total positions of person(s) subject to the notification obligation</span></p>\n</td>\n</tr>\n<tr class=\"go\">\n<td class=\"gn\" colspan=\"2\" style=\"width:127\">\n<p class=\"a\"><span class=\"if\"><br/></span></p>\n</td>\n<td class=\"gm\" colspan=\"4\" style=\"width:127\">\n<p class=\"jd\"><span class=\"ij\">% of voting rights attached to shares (total of 8. A)</span></p>\n</td>\n<td class=\"gl\" colspan=\"5\" style=\"width:140\">\n<p class=\"jd\"><span class=\"ij\">% of </span><span class=\"ij\">voting rights through </span><span class=\"ij\">financial instruments<br/>\n(total of 8.B 1 + 8.B 2)</span></p>\n</td>\n<td class=\"gk\" colspan=\"2\" style=\"width:127\">\n<p class=\"jd\"><span class=\"ij\">Total of both in % (8.A + 8.B)</span></p>\n</td>\n<td class=\"gj\" colspan=\"2\" style=\"width:114\">\n<p class=\"a\"><span class=\"ij\">Total number of voting rights of issuer</span><sup><span class=\"ie\">vii</span></sup></p>\n</td>\n</tr>\n<tr class=\"go\">\n<td class=\"gn\" colspan=\"2\" style=\"width:127\">\n<p class=\"a\"><span class=\"ij\">Resulting situation on the date on which threshold was crossed or reached</span></p>\n</td>\n<td class=\"gm\" colspan=\"4\" style=\"width:127\">\n<p class=\"a\"><span class=\"if\">61.40%</span></p>\n</td>\n<td class=\"gl\" colspan=\"5\" style=\"width:140\">\n<p class=\"a\"><span class=\"if\">0</span></p>\n</td>\n<td class=\"gk\" colspan=\"2\" style=\"width:127\">\n<p class=\"a\"><span class=\"if\">61.40%</span></p>\n</td>\n<td class=\"gj\" colspan=\"2\" style=\"width:114\">\n<p class=\"a\"><span class=\"if\">176\u00a0471 625</span></p>\n</td>\n</tr>\n<tr class=\"gd\">\n<td class=\"gi\" colspan=\"2\" style=\"width:127\">\n<p class=\"a\"><span class=\"ij\">Position of previous notification (if </span></p>\n<p class=\"a\"><span class=\"ij\">applicable)</span></p>\n</td>\n<td class=\"gh\" colspan=\"4\" style=\"width:127\">\n<p class=\"a\"><span class=\"if\">60.2762%</span></p>\n</td>\n<td class=\"gg\" colspan=\"5\" style=\"width:140\">\n<p class=\"a\"><span class=\"if\">0</span></p>\n</td>\n<td class=\"gf\" colspan=\"2\" style=\"width:127\">\n<p class=\"a\"><span class=\"if\">60.2762%</span></p>\n</td>\n<td class=\"ge\" colspan=\"2\" style=\"width:114\">\n<p class=\"a\"><span class=\"if\"><br/></span></p>\n</td>\n</tr>\n<tr class=\"gb\">\n<td class=\"gc\" colspan=\"15\" style=\"width:694\">\n<p class=\"a\"><span style=\"font-weight:bold\"><span class=\"if\">8. Notified details of the resulting situation on the date on which the threshold was crossed or reached</span></span><sup><span class=\"ie\">viii</span></sup></p>\n</td>\n</tr>\n<tr class=\"fz\">\n<td class=\"ga\" colspan=\"15\" style=\"width:694\">\n<p class=\"je\"><span class=\"if\">A: Voting rights attached to shares</span></p>\n</td>\n</tr>\n<tr class=\"fv\">\n<td class=\"fy\" colspan=\"3\" rowspan=\"2\" style=\"width:133\">\n<p class=\"je\"><span class=\"ij\">Class/type of<br/>\nshares</span></p>\n<p class=\"a\"><span class=\"ij\">ISIN code (if possible)</span></p>\n</td>\n<td class=\"fx\" colspan=\"7\" style=\"width:256\">\n<p class=\"a\"><span style=\"font-weight:bold\"><span class=\"ij\">Number of voting rights</span></span><sup><span class=\"hg\">ix</span></sup></p>\n</td>\n<td class=\"fw\" colspan=\"5\" style=\"width:276\">\n<p class=\"je\"><span class=\"ij\">% of voting rights</span></p>\n</td>\n</tr>\n<tr class=\"fp\">\n<td class=\"ft\" colspan=\"2\" style=\"width:120\">\n<p class=\"jf\"><span class=\"ij\">Direct</span></p>\n<p class=\"jd\"><span class=\"in\">(Art 9 of Directive 2004/109/EC) (DTR5.1)</span></p>\n</td>\n<td class=\"fs\" colspan=\"5\" style=\"width:121\">\n<p class=\"jf\"><span class=\"ij\">Indirect</span></p>\n<p class=\"jd\"><span class=\"in\">(Art 10 of Directive 2004/109/EC) (DTR5.2.1)</span></p>\n</td>\n<td class=\"fr\" colspan=\"3\" style=\"width:141\">\n<p class=\"jf\"><span class=\"ij\">Direct</span></p>\n<p class=\"jd\"><span class=\"in\">(Art 9 of Directive 2004/109/EC) (DTR5.1)</span></p>\n</td>\n<td class=\"fq\" colspan=\"2\" style=\"width:121\">\n<p class=\"jf\"><span class=\"ij\">Indirect</span></p>\n<p class=\"jd\"><span class=\"in\">(Art 10 of Directive 2004/109/EC) (DTR5.2.1)</span></p>\n</td>\n</tr>\n<tr class=\"fi\">\n<td class=\"fn\" colspan=\"3\" style=\"width:133\">\n<p class=\"a\"><span class=\"fo\">GB00BBG9VN75</span></p>\n</td>\n<td class=\"fm\" colspan=\"2\" style=\"width:120\">\n<p class=\"a\"><span class=\"if\">-</span></p>\n</td>\n<td class=\"fl\" colspan=\"5\" style=\"width:121\">\n<p class=\"a\"><span class=\"if\">176\u00a0471 625</span></p>\n</td>\n<td class=\"fk\" colspan=\"3\" style=\"width:141\">\n<p class=\"a\"><span class=\"if\">-</span></p>\n</td>\n<td class=\"fj\" colspan=\"2\" style=\"width:121\">\n<p class=\"a\"><span class=\"if\">61.40%</span></p>\n</td>\n</tr>\n<tr class=\"fi\">\n<td class=\"fn\" colspan=\"3\" style=\"width:133\">\n<p class=\"a\"><span class=\"if\"><br/></span></p>\n</td>\n<td class=\"fm\" colspan=\"2\" style=\"width:120\">\n<p class=\"a\"><span class=\"if\"><br/></span></p>\n</td>\n<td class=\"fl\" colspan=\"5\" style=\"width:121\">\n<p class=\"a\"><span class=\"if\"><br/></span></p>\n</td>\n<td class=\"fk\" colspan=\"3\" style=\"width:141\">\n<p class=\"a\"><span class=\"if\"><br/></span></p>\n</td>\n<td class=\"fj\" colspan=\"2\" style=\"width:121\">\n<p class=\"a\"><span class=\"if\"><br/></span></p>\n</td>\n</tr>\n<tr class=\"fi\">\n<td class=\"fn\" colspan=\"3\" style=\"width:133\">\n<p class=\"a\"><span class=\"if\"><br/></span></p>\n</td>\n<td class=\"fm\" colspan=\"2\" style=\"width:120\">\n<p class=\"a\"><span class=\"if\"><br/></span></p>\n</td>\n<td class=\"fl\" colspan=\"5\" style=\"width:121\">\n<p class=\"a\"><span class=\"if\"><br/></span></p>\n</td>\n<td class=\"fk\" colspan=\"3\" style=\"width:141\">\n<p class=\"a\"><span class=\"if\"><br/></span></p>\n</td>\n<td class=\"fj\" colspan=\"2\" style=\"width:121\">\n<p class=\"a\"><span class=\"if\"><br/></span></p>\n</td>\n</tr>\n<tr class=\"fi\">\n<td class=\"fn\" colspan=\"3\" style=\"width:133\">\n<p class=\"je\"><span class=\"ij\">SUBTOTAL 8. A</span></p>\n</td>\n<td class=\"fh\" colspan=\"7\" style=\"width:256\">\n<p class=\"jd\"><span class=\"if\">176\u00a0471 625</span></p>\n</td>\n<td class=\"fg\" colspan=\"5\" style=\"width:276\">\n<p class=\"jd\"><span class=\"if\">61.40%</span></p>\n</td>\n</tr>\n<tr class=\"fe\">\n<td class=\"ff\" colspan=\"15\" style=\"width:694\">\n<p class=\"a\"><span class=\"if\">\u00a0</span></p>\n<p class=\"a\"><span class=\"if\">\u00a0</span></p>\n</td>\n</tr>\n<tr class=\"fc\">\n<td class=\"fd\" colspan=\"15\" style=\"width:694\">\n<p class=\"je\"><span class=\"if\">B 1: Financial Instruments according to Art. 13(1)(a) of Directive 2004/109/EC (DTR5.3.1.1 (a))</span></p>\n</td>\n</tr>\n<tr>\n<td class=\"fb\" colspan=\"3\" style=\"width:133\">\n<p class=\"je\"><span class=\"ij\">Type of financial instrument</span></p>\n</td>\n<td class=\"fa\" style=\"width:68\">\n<p class=\"a\"><span style=\"font-weight:bold\"><span class=\"ij\">Expiration<br/>\ndate</span></span><sup><span class=\"in\">x</span></sup></p>\n</td>\n<td class=\"ey\" colspan=\"5\" style=\"width:156\">\n<p class=\"a\"><span style=\"font-weight:bold\"><span class=\"ij\">Exercise/<br/>\nConversion Period</span></span><sup><span class=\"ez\">xi</span></sup></p>\n</td>\n<td class=\"ex\" colspan=\"4\" style=\"width:158\">\n<p class=\"je\"><span class=\"ij\">Number of voting rights that may be acquired if the instrument is </span></p>\n<p class=\"je\"><span class=\"ij\">exercised/converted.</span></p>\n</td>\n<td class=\"ew\" colspan=\"2\" style=\"width:121\">\n<p class=\"je\"><span class=\"ij\">% of voting rights</span></p>\n</td>\n</tr>\n<tr class=\"eq\">\n<td class=\"ev\" colspan=\"3\" style=\"width:133\">\n<p class=\"a\"><span class=\"if\"><br/></span></p>\n</td>\n<td class=\"eu\" style=\"width:68\">\n<p class=\"a\"><span class=\"if\"><br/></span></p>\n</td>\n<td class=\"et\" colspan=\"5\" style=\"width:156\">\n<p class=\"a\"><span class=\"if\"><br/></span></p>\n</td>\n<td class=\"es\" colspan=\"4\" style=\"width:158\">\n<p class=\"a\"><span class=\"if\"><br/></span></p>\n</td>\n<td class=\"er\" colspan=\"2\" style=\"width:121\">\n<p class=\"a\"><span class=\"if\"><br/></span></p>\n</td>\n</tr>\n<tr class=\"eq\">\n<td class=\"ev\" colspan=\"3\" style=\"width:133\">\n<p class=\"a\"><span class=\"if\"><br/></span></p>\n</td>\n<td class=\"eu\" style=\"width:68\">\n<p class=\"a\"><span class=\"if\"><br/></span></p>\n</td>\n<td class=\"et\" colspan=\"5\" style=\"width:156\">\n<p class=\"a\"><span class=\"if\"><br/></span></p>\n</td>\n<td class=\"es\" colspan=\"4\" style=\"width:158\">\n<p class=\"a\"><span class=\"if\"><br/></span></p>\n</td>\n<td class=\"er\" colspan=\"2\" style=\"width:121\">\n<p class=\"a\"><span class=\"if\"><br/></span></p>\n</td>\n</tr>\n<tr class=\"eq\">\n<td class=\"ev\" colspan=\"3\" style=\"width:133\">\n<p class=\"a\"><span class=\"if\"><br/></span></p>\n</td>\n<td class=\"eu\" style=\"width:68\">\n<p class=\"a\"><span class=\"if\"><br/></span></p>\n</td>\n<td class=\"et\" colspan=\"5\" style=\"width:156\">\n<p class=\"a\"><span class=\"if\"><br/></span></p>\n</td>\n<td class=\"es\" colspan=\"4\" style=\"width:158\">\n<p class=\"a\"><span class=\"if\"><br/></span></p>\n</td>\n<td class=\"er\" colspan=\"2\" style=\"width:121\">\n<p class=\"a\"><span class=\"if\"><br/></span></p>\n</td>\n</tr>\n<tr class=\"eq\">\n<td class=\"ep\" colspan=\"3\" style=\"width:133\">\n<p class=\"a\"><span class=\"if\"><br/></span></p>\n</td>\n<td class=\"eo\" style=\"width:68\">\n<p class=\"a\"><span class=\"if\"><br/></span></p>\n</td>\n<td class=\"et\" colspan=\"5\" style=\"width:156\">\n<p class=\"je\"><span class=\"ij\">SUBTOTAL 8. B 1</span></p>\n</td>\n<td class=\"es\" colspan=\"4\" style=\"width:158\">\n<p class=\"a\"><span class=\"if\"><br/></span></p>\n</td>\n<td class=\"er\" colspan=\"2\" style=\"width:121\">\n<p class=\"a\"><span class=\"if\"><br/></span></p>\n</td>\n</tr>\n<tr class=\"fe\">\n<td class=\"ff\" colspan=\"15\" style=\"width:694\">\n<p class=\"a\"><span class=\"if\">\u00a0</span></p>\n<p class=\"a\"><span class=\"if\">\u00a0</span></p>\n</td>\n</tr>\n<tr class=\"em\">\n<td class=\"en\" colspan=\"15\" style=\"width:694\">\n<p class=\"je\"><span class=\"if\">B 2: Financial Instruments with similar economic effect according to Art. 13(1)(b) of Directive 2004/109/EC (DTR5.3.1.1 (b))</span></p>\n</td>\n</tr>\n<tr>\n<td class=\"el\" style=\"width:105\">\n<p class=\"je\"><span class=\"ij\">Type of financial instrument</span></p>\n</td>\n<td class=\"ek\" colspan=\"3\" style=\"width:96\">\n<p class=\"a\"><span style=\"font-weight:bold\"><span class=\"ij\">Expiration<br/>\ndate</span></span><sup><span class=\"in\">x</span></sup></p>\n</td>\n<td class=\"ej\" colspan=\"3\" style=\"width:105\">\n<p class=\"a\"><span style=\"font-weight:bold\"><span class=\"ij\">Exercise/<br/>\nConversion Period </span></span><sup><span class=\"hg\">xi</span></sup></p>\n</td>\n<td class=\"ei\" colspan=\"5\" style=\"width:104\">\n<p class=\"je\"><span class=\"ij\">Physical or cash </span></p>\n<p class=\"a\"><span style=\"font-weight:bold\"><span class=\"ij\">settlement</span></span><sup><span class=\"in\">xii</span></sup></p>\n</td>\n<td class=\"eh\" style=\"width:92\">\n<p class=\"je\"><span class=\"ij\">Number of voting rights </span></p>\n</td>\n<td class=\"eg\" colspan=\"2\" style=\"width:121\">\n<p class=\"je\"><span class=\"ij\">% of voting rights</span></p>\n</td>\n</tr>\n<tr class=\"eq\">\n<td class=\"ef\" style=\"width:105\">\n<p class=\"a\"><span class=\"if\"><br/></span></p>\n</td>\n<td class=\"ee\" colspan=\"3\" style=\"width:96\">\n<p class=\"a\"><span class=\"if\"><br/></span></p>\n</td>\n<td class=\"ed\" colspan=\"3\" style=\"width:105\">\n<p class=\"a\"><span class=\"if\"><br/></span></p>\n</td>\n<td class=\"ec\" colspan=\"5\" style=\"width:104\">\n<p class=\"a\"><span class=\"if\"><br/></span></p>\n</td>\n<td class=\"eb\" style=\"width:92\">\n<p class=\"a\"><span class=\"if\"><br/></span></p>\n</td>\n<td class=\"ea\" colspan=\"2\" style=\"width:121\">\n<p class=\"a\"><span class=\"if\"><br/></span></p>\n</td>\n</tr>\n<tr class=\"eq\">\n<td class=\"dz\" style=\"width:105\">\n<p class=\"a\"><span class=\"if\"><br/></span></p>\n</td>\n<td class=\"dy\" colspan=\"3\" style=\"width:96\">\n<p class=\"a\"><span class=\"if\"><br/></span></p>\n</td>\n<td class=\"dx\" colspan=\"3\" style=\"width:105\">\n<p class=\"a\"><span class=\"if\"><br/></span></p>\n</td>\n<td class=\"dw\" colspan=\"5\" style=\"width:104\">\n<p class=\"a\"><span class=\"if\"><br/></span></p>\n</td>\n<td class=\"eb\" style=\"width:92\">\n<p class=\"a\"><span class=\"if\"><br/></span></p>\n</td>\n<td class=\"ea\" colspan=\"2\" style=\"width:121\">\n<p class=\"a\"><span class=\"if\"><br/></span></p>\n</td>\n</tr>\n<tr class=\"eq\">\n<td class=\"dz\" style=\"width:105\">\n<p class=\"a\"><span class=\"if\"><br/></span></p>\n</td>\n<td class=\"dy\" colspan=\"3\" style=\"width:96\">\n<p class=\"a\"><span class=\"if\"><br/></span></p>\n</td>\n<td class=\"dx\" colspan=\"3\" style=\"width:105\">\n<p class=\"a\"><span class=\"if\"><br/></span></p>\n</td>\n<td class=\"dw\" colspan=\"5\" style=\"width:104\">\n<p class=\"a\"><span class=\"if\"><br/></span></p>\n</td>\n<td class=\"eb\" style=\"width:92\">\n<p class=\"a\"><span class=\"if\"><br/></span></p>\n</td>\n<td class=\"ea\" colspan=\"2\" style=\"width:121\">\n<p class=\"a\"><span class=\"if\"><br/></span></p>\n</td>\n</tr>\n<tr class=\"eq\">\n<td class=\"dv\" style=\"width:105\">\n<p class=\"a\"><span class=\"if\"><br/></span></p>\n</td>\n<td class=\"du\" colspan=\"3\" style=\"width:96\">\n<p class=\"a\"><span class=\"if\"><br/></span></p>\n</td>\n<td class=\"dt\" colspan=\"3\" style=\"width:105\">\n<p class=\"je\"><span class=\"ij\"><br/></span></p>\n</td>\n<td class=\"dw\" colspan=\"5\" style=\"width:104\">\n<p class=\"je\"><span class=\"ij\">SUBTOTAL 8.B.2</span></p>\n</td>\n<td class=\"eb\" style=\"width:92\">\n<p class=\"a\"><span class=\"if\"><br/></span></p>\n</td>\n<td class=\"ea\" colspan=\"2\" style=\"width:121\">\n<p class=\"a\"><span class=\"if\"><br/></span></p>\n</td>\n</tr>\n<tr class=\"fe\">\n<td class=\"ff\" colspan=\"15\" style=\"width:694\">\n<p class=\"a\"><span class=\"if\">\u00a0</span></p>\n<p class=\"a\"><span class=\"if\">\u00a0</span></p>\n<p class=\"a\"><span class=\"if\">\u00a0</span></p>\n</td>\n</tr>\n<tr style=\"height:0\">\n<td class=\"ds\" style=\"width:106\">\n</td><td class=\"ds\" style=\"width:22\">\n</td><td class=\"ds\" style=\"width:6\">\n</td><td class=\"ds\" style=\"width:79\">\n</td><td class=\"ds\" style=\"width:53\">\n</td><td class=\"ds\" style=\"width:1\">\n</td><td class=\"ds\" style=\"width:52\">\n</td><td class=\"ds\" style=\"width:40\">\n</td><td class=\"ds\" style=\"width:12\">\n</td><td class=\"ds\" style=\"width:32\">\n</td><td class=\"ds\" style=\"width:5\">\n</td><td class=\"ds\" style=\"width:15\">\n</td><td class=\"ds\" style=\"width:121\">\n</td><td class=\"ds\" style=\"width:119\">\n</td><td class=\"ds\" style=\"width:46\">\n</td></tr>\n</table></div>\n<p class=\"a\">\u00a0</p>\n<div class=\"story-table-container\"><table cellpadding=\"0\" cellspacing=\"0\" class=\"iz\" style=\"width:714\">\n<tr class=\"dp\">\n<td class=\"dq\" colspan=\"7\" style=\"width:700\">\n<p class=\"a\"><span style=\"font-weight:bold\"><span class=\"if\">9. Information in relation to the person subject to the notification obligation </span></span><span class=\"if\">(please mark the </span></p>\n<p class=\"a\"><span class=\"if\">applicable box with an \"X\")</span></p>\n</td>\n</tr>\n<tr class=\"dm\">\n<td class=\"do\" colspan=\"5\" style=\"width:654\">\n<p class=\"a\"><span class=\"ij\">Person subject to the notification obligation is not controlled by any natural person or legal entity and does not control any other undertaking(s) holding directly or indirectly an interest in the (underlying) issuer</span><sup><span class=\"ij\">xiii</span></sup></p>\n</td>\n<td class=\"dn\" colspan=\"2\" style=\"width:31\">\n<p class=\"jd\"><span class=\"if\"><br/></span></p>\n</td>\n</tr>\n<tr class=\"dg\">\n<td class=\"di\" colspan=\"5\" style=\"width:654\">\n<p class=\"a\"><span class=\"dl\">Full</span><span class=\"ij\"> chain of controlled undertakings through which the voting rights and/or the<br/>\nfinancial instruments are effectively held starting with the ultimate controlling natural person or legal entity</span><sup><span class=\"dk\">xiv </span></sup><span class=\"dj\">(please add additional rows as necessary)</span></p>\n</td>\n<td class=\"dh\" colspan=\"2\" style=\"width:31\">\n<p class=\"jd\"><span class=\"if\">X</span></p>\n</td>\n</tr>\n<tr class=\"db\">\n<td class=\"df\" style=\"width:168\">\n<p class=\"jd\"><span style=\"font-weight:bold\"><span class=\"if\">Name</span></span><sup><span class=\"in\">xv</span></sup></p>\n</td>\n<td class=\"de\" style=\"width:163\">\n<p class=\"jf\"><span class=\"if\">% of voting rights if it equals or is higher than the notifiable threshold</span></p>\n</td>\n<td class=\"dd\" colspan=\"2\" style=\"width:163\">\n<p class=\"jf\"><span class=\"if\">% of voting rights through financial instruments if it equals or is higher than the notifiable threshold</span></p>\n</td>\n<td class=\"dd\" colspan=\"2\" style=\"width:163\">\n<p class=\"jf\"><span class=\"if\">Total of both if it equals or is higher than the notifiable threshold</span></p>\n</td>\n<td class=\"dc\" style=\"width:1\">\n<p class=\"a\">\u00a0</p>\n</td>\n</tr>\n<tr class=\"hm\">\n<td class=\"da\" style=\"width:168\">\n<p class=\"a\"><span class=\"if\">Schneider Electric SE</span></p>\n</td>\n<td class=\"cz\" style=\"width:163\">\n<p class=\"a\"><span class=\"if\">N/A</span></p>\n</td>\n<td class=\"cy\" colspan=\"2\" style=\"width:163\">\n<p class=\"a\"><span class=\"if\">N/A</span></p>\n</td>\n<td class=\"cy\" colspan=\"2\" style=\"width:163\">\n<p class=\"a\"><span class=\"if\">N/A</span></p>\n</td>\n<td class=\"dc\" style=\"width:1\">\n<p class=\"a\">\u00a0</p>\n</td>\n</tr>\n<tr class=\"hm\">\n<td class=\"da\" style=\"width:168\">\n<p class=\"a\"><span class=\"if\">Schneider Electric Industries SAS</span></p>\n</td>\n<td class=\"cz\" style=\"width:163\">\n<p class=\"a\"><span class=\"if\">N/A</span></p>\n</td>\n<td class=\"cy\" colspan=\"2\" style=\"width:163\">\n<p class=\"a\"><span class=\"if\">N/A</span></p>\n</td>\n<td class=\"cy\" colspan=\"2\" style=\"width:163\">\n<p class=\"a\"><span class=\"if\">N/A</span></p>\n</td>\n<td class=\"dc\" style=\"width:1\">\n<p class=\"a\">\u00a0</p>\n</td>\n</tr>\n<tr class=\"hm\">\n<td class=\"da\" style=\"width:168\">\n<p class=\"a\"><span class=\"if\">Samos Acquisition Company Limited</span></p>\n</td>\n<td class=\"cz\" style=\"width:163\">\n<p class=\"a\"><span class=\"if\">61.40%</span></p>\n</td>\n<td class=\"cy\" colspan=\"2\" style=\"width:163\">\n<p class=\"a\"><span class=\"if\">N/A</span></p>\n</td>\n<td class=\"cy\" colspan=\"2\" style=\"width:163\">\n<p class=\"a\"><span class=\"if\">61.40%</span></p>\n</td>\n<td class=\"dc\" style=\"width:1\">\n<p class=\"a\">\u00a0</p>\n</td>\n</tr>\n<tr class=\"hm\">\n<td class=\"da\" style=\"width:168\">\n<p class=\"a\"><span class=\"if\"><br/></span></p>\n</td>\n<td class=\"cz\" style=\"width:163\">\n<p class=\"a\"><span class=\"if\"><br/></span></p>\n</td>\n<td class=\"cy\" colspan=\"2\" style=\"width:163\">\n<p class=\"a\"><span class=\"if\"><br/></span></p>\n</td>\n<td class=\"cy\" colspan=\"2\" style=\"width:163\">\n<p class=\"a\"><span class=\"if\"><br/></span></p>\n</td>\n<td class=\"dc\" style=\"width:1\">\n<p class=\"a\">\u00a0</p>\n</td>\n</tr>\n<tr class=\"hm\">\n<td class=\"da\" style=\"width:168\">\n<p class=\"a\"><span class=\"if\"><br/></span></p>\n</td>\n<td class=\"cz\" style=\"width:163\">\n<p class=\"a\"><span class=\"if\"><br/></span></p>\n</td>\n<td class=\"cy\" colspan=\"2\" style=\"width:163\">\n<p class=\"a\"><span class=\"if\"><br/></span></p>\n</td>\n<td class=\"cy\" colspan=\"2\" style=\"width:163\">\n<p class=\"a\"><span class=\"if\"><br/></span></p>\n</td>\n<td class=\"cx\" style=\"width:1\">\n<p class=\"a\">\u00a0</p>\n</td>\n</tr>\n<tr class=\"cv\">\n<td class=\"cw\" colspan=\"7\" style=\"width:700\">\n<p class=\"je\"><span class=\"if\"><br/></span></p>\n</td>\n</tr>\n<tr class=\"cs\">\n<td class=\"ct\" colspan=\"7\" style=\"width:700\">\n<p class=\"ja\"><span style=\"font-weight:bold\"><span class=\"ir\">10. </span></span><span style=\"font-weight:bold\"><span class=\"cu\">In case of proxy voting, please identify:</span></span></p>\n</td>\n</tr>\n<tr class=\"cp\">\n<td class=\"cr\" colspan=\"3\" style=\"width:346\">\n<p class=\"ja\"><span class=\"if\">Name of the proxy holder</span></p>\n</td>\n<td class=\"cq\" colspan=\"4\" style=\"width:340\">\n<p class=\"ja\"><span class=\"if\"><br/></span></p>\n</td>\n</tr>\n<tr class=\"go\">\n<td class=\"co\" colspan=\"3\" style=\"width:346\">\n<p class=\"ja\"><span class=\"if\">The number and % of voting rights held</span></p>\n</td>\n<td class=\"cn\" colspan=\"4\" style=\"width:340\">\n<p class=\"ja\"><span class=\"if\"><br/></span></p>\n</td>\n</tr>\n<tr class=\"ck\">\n<td class=\"cm\" colspan=\"3\" style=\"width:346\">\n<p class=\"ja\"><span class=\"if\">The date until which the voting rights will be held</span></p>\n</td>\n<td class=\"cl\" colspan=\"4\" style=\"width:340\">\n<p class=\"ja\"><span class=\"if\"><br/></span></p>\n</td>\n</tr>\n<tr class=\"fc\">\n<td class=\"cj\" colspan=\"7\" style=\"width:700\">\n<p class=\"a\"><span class=\"if\"><br/></span></p>\n</td>\n</tr>\n<tr class=\"ch\">\n<td class=\"ci\" colspan=\"7\" style=\"width:700\">\n<p class=\"a\"><span style=\"font-weight:bold\"><span class=\"if\">11. Additional information</span></span><sup><span class=\"ie\">xvi</span></sup></p>\n</td>\n</tr>\n<tr class=\"cf\">\n<td class=\"cg\" colspan=\"7\" style=\"width:700\">\n<p class=\"a\"><span class=\"if\"><br/></span></p>\n</td>\n</tr>\n<tr style=\"height:0\">\n<td class=\"ds\" style=\"width:171\">\n</td><td class=\"ds\" style=\"width:166\">\n</td><td class=\"ds\" style=\"width:16\">\n</td><td class=\"ds\" style=\"width:150\">\n</td><td class=\"ds\" style=\"width:164\">\n</td><td class=\"ds\" style=\"width:2\">\n</td><td class=\"ds\" style=\"width:45\">\n</td></tr>\n</table></div>\n<p class=\"a\">\u00a0</p>\n<div class=\"story-table-container\"><table cellpadding=\"0\" cellspacing=\"0\" class=\"jg\" style=\"width:709\">\n<tr class=\"cc\">\n<td class=\"ce\" style=\"width:146\">\n<p class=\"je\"><span class=\"if\">Place of completion</span></p>\n</td>\n<td class=\"cd\" style=\"width:534\">\n<p class=\"a\"><span class=\"if\">Telford</span></p>\n</td>\n</tr>\n<tr class=\"bz\">\n<td class=\"cb\" style=\"width:146\">\n<p class=\"je\"><span class=\"if\">Date of completion</span></p>\n</td>\n<td class=\"ca\" style=\"width:534\">\n<p class=\"a\"><span class=\"if\">December 10, 2020</span></p>\n</td>\n</tr>\n</table></div>\n<p class=\"a\">\u00a0</p>\n</div>\n<div style=\"text-align:left;font-size:10pt\"><div>This information is provided by RNS, the news service of the London Stock Exchange. RNS is approved by the Financial Conduct Authority to act as a Primary Information Provider in the United Kingdom. Terms and conditions relating to the use and distribution of this information may apply. For further information, please contact <a href=\"mailto:rns@lseg.com\" data-type=\"email\" translate=\"no\">rns@lseg.com</a> or visit <a href=\"http://www.rns.com/\" data-type=\"url\" class=\"tr-link\" translate=\"no\">www.rns.com</a>.<br/><br/>RNS may use your IP address to confirm compliance with the terms and conditions, to analyse how you engage with the information contained in this communication, and to share such analysis on an anonymised basis with others as part of our commercial services. For further information about how RNS and the London Stock Exchange use the personal data you provide us, please see our <a href=\"https://www.lseg.com/privacy-and-cookie-policy\" data-type=\"url\" class=\"tr-link\" translate=\"no\">Privacy Policy</a>.</div><div>\u00a0</div>  END</div><div>\u00a0</div><div>\u00a0</div>HOLBGBDDDDBDGGB</div>"}