{"date": "2021-11-24 19:42:25.508000+00:00", "ticker": "AMZN", "mrkt_info": {"open": 3580.04, "close": 3504.56}, "html": "<div class=\"storyContent\" lang=\"en\"><style type=\"text/css\">.storyContent * {border-color:inherit !important;outline-color:inherit !important;}</style><div class=\"tr-npp-body\">\n<pre>MACE SECURITY INTERNATIONAL INC (\"MACE-0\")\n- To Webcast Live at Small Cap Growth -\n- VirtualInvestorConferences.com December 2nd , 2021,\n- 9:30 AM (EST)\n\n Mace(R) Security International, Inc. based in Cleveland, Ohio focused on\npersonal safety products, today announced that Gary Medved, CEO and\nPresident, will present live at VirtualInvestorConferences.com on December\n2nd, 2021.\n\n DATE: December 2nd, 2021  TIME: 9:30 AM (EST)  LINK:\n<a href=\"https://bit.ly/3Cka9xR\" data-type=\"url\" class=\"tr-link\" translate=\"no\">https://bit.ly/3Cka9xR</a>\n\n This will be a live, interactive online event where investors are invited\nto ask the company questions in real-time. If attendees are not able to\njoin the event live on the day of the conference, an archived webcast will\nalso be made available after the event.\n\n It is recommended that investors pre-register and run the online system\ncheck to expedite participation and receive event updates.\n\n Learn more about the event at www.virtualinvestorconferences.com.\n\n About Mace(R) Security International, Inc. Mace(R) Security International,\nInc. (MACE) is a globally recognized leader in personal safety and\nsecurity. Based in Cleveland, Ohio, the company has spent more than 40\nyears designing and manufacturing consumer and tactical products for\npersonal defense and security under its world-renowned Mace(R) Brand - the\noriginal trusted brand of defense spray products. The company also offers\naerosol defense sprays and tactical products for law enforcement and\nsecurity professionals worldwide through its Mace(R) Take Down(R) brand,\nKUROS!(R) Brand personal safety products, Vigilant(R) Brand alarms, and\nTornado(R) Brand pepper spray and stun guns. MACE(R) distributes and\nsupports Mace(R) Brand products through mass market retailers, wholesale\ndistributors, independent dealers, Amazon.com, Mace.com, and other\nchannels. For more information, visit www.mace.com.\n\n About Virtual Investor Conferences(R) Virtual Investor Conferences (VIC)\nis the leading proprietary investor conference series that provides an\ninteractive forum for publicly-traded companies to meet and present\ndirectly with investors.\n\n A real-time solution for investor engagement, Virtual Investor Conferences\nis part of OTC Market Group's suite of investor relations services\nspecifically designed for more efficient Investor Access.  Replicating the\nlook and feel of on-site investor conferences, Virtual Investor Conferences\ncombine leading-edge conferencing and investor communications capabilities\nwith a comprehensive global investor audience network.\n                         ______________________________________\n       _______________________________________________\n\n     ____________________________________________________________   \n      (c)2021 Market News Publishing Inc.  All rights reserved.    \n Toronto:(416)366-8881   Vancouver:(604)689-1101   Fax:(604)689-1106\n\n     2132700667.MNPRE2132702187-11270920211124</pre>\n</div><p class=\"line-break\"><br/></p><p class=\"tr-copyright\">Copyright (c) 2021 Thomson Reuters Limited.</p></div>"}