{"date": "2021-11-26 08:44:43.743000+00:00", "ticker": "AMZN", "mrkt_info": {"open": 3580.41, "close": 3561.57}, "html": "<div class=\"storyContent\" lang=\"en\"><style type=\"text/css\">.storyContent * {border-color:inherit !important;outline-color:inherit !important;}</style><p class=\"tr-story-p1\"><span class=\"tr-dateline\">PARIS, Nov 26 (Reuters)</span><span class=\"tr-dl-sep\"> - </span>One of France's top labour union, CGT, called for Amazon workers in the country to go on strike to coincide with Black Friday discount shopping sales, joining labour protests against the company planned in other European countries.</p><p>German union Verdi on Wednesday called on employees to strike at three different Amazon locations in Germany. <span> (<a href=\"reuters://REALTIME/verb=NewsStory/ric=nFWN2SF0U3\" data-type=\"storyId\" data-story-id=\"nFWN2SF0U3\" translate=\"no\" dir=\"ltr\" class=\"tr-pnac\">Full Story</a>)</span></p><p>     </p><p>       </p><p><br/></p><p class=\"tr-signoff\"> (Reporting by Mathieu Rosemain, writing by  Silvia Aloisi; editing by Richard Lough)</p><p class=\"tr-contactinfo\">(( <a href=\"mailto:silvia.aloisi@thomsonreuters.com\" data-type=\"email\" translate=\"no\">silvia.aloisi@thomsonreuters.com</a> ; +393487607044; Reuters Messaging: <a class=\"tr-link tr-link-rm\" href=\"rm://silvia.aloisi.thomsonreuters.com@reuters.net\">silvia.aloisi.thomsonreuters.com@reuters.net</a> ))</p><p class=\"line-break\"><br/></p><p class=\"tr-copyright\">(c) Copyright Thomson Reuters 2021. Click For Restrictions - https://agency.reuters.com/en/copyright.html</p><p class=\"line-break\"><br/></p><p class=\"tr-slugline\">Keywords: AMAZON-FRANCE/STRIKE (URGENT)</p></div>"}