{"date": "2021-12-17 13:33:03.763000+00:00", "ticker": "AMZN", "mrkt_info": {"open": 3466.3, "close": 3400.35}, "html": "<div class=\"storyContent\" lang=\"en\"><p>Dec 17 (Reuters) - :\r\n<br/>*INDIA'S FUTURE GROUP IS UNLIKELY TO COOPERATE WITH AMAZON IF IT TRIES TO REAPPLY FOR ANTITRUST CLEARANCE AFTER 2019 DEAL SUSPENDED-SOURCE\r\n*FUTURE GROUP WILL LIKELY TAKE ANTITRUST SUSPENSION OF 2019 AMAZON DEAL TO LEGAL FORUMS, SAY AMAZON HAS NO LEGAL BASIS TO CHALLENGE ASSETS SALE-SOURCE\r\n*Further company coverage: AMZN.O</p><ul class=\"bulleted-list arrowlist\"><li>((<a href=\"mailto:Reuters.Briefs@thomsonreuters.com\" data-type=\"email\" translate=\"no\">Reuters.Briefs@thomsonreuters.com</a>;))</li></ul><p>((Reuters Investor Briefs; email: <a href=\"mailto:reutersinvestor.briefs@thomsonreuters.com\" data-type=\"email\" translate=\"no\">reutersinvestor.briefs@thomsonreuters.com</a>))\r\nSource Date/Time = 17-DEC-202113:15:00.07 GMT</p></div>"}