{"date": "2021-10-02 09:52:14.633000+00:00", "ticker": "ABDN", "mrkt_info": {"open": 255.6, "close": 248.5}, "html": "<div class=\"storyContent\" lang=\"en\"><style type=\"text/css\">.storyContent * {border-color:inherit !important;outline-color:inherit !important;}</style><div class=\"tr-npp-lead\"><p>UK\u0092s Standard Life Investments on Wednesday offloaded 5 per cent stake in HDFC Mutual Fund.</p><p>It sold 10.65 million shares at Rs 2,873.8 apiece for a total of Rs 3,061 crore, data provided by BSE showed.</p></div><div class=\"tr-npp-body\"><p>T Rowe Price Emerging Markets Stock Fund picked up about 1.52 million shares for Rs 436 crore.</p><p>Names of other buyers were not known. Shares of HDFC MF fell 5.6 per cent to close at Rs 2,905.</p><p>Prior to the stake sale, Standard Life held 21.23 per cent stake in HDFC MF, while mortgage lender HDFC held 52.65 per cent stake.</p></div><p class=\"line-break\"><br/></p><p class=\"tr-copyright\">Copyright (c) 2021 Business Standard Ltd.</p></div>"}