{"date": "2021-12-02 10:40:17.849000+00:00", "ticker": "ABDN", "mrkt_info": {"open": 233.3, "close": 230.0}, "html": "<div class=\"storyContent\" lang=\"en\"><style type=\"text/css\">.storyContent * {border-color:inherit !important;outline-color:inherit !important;}</style><p class=\"tr-story-p1\"><span class=\"tr-dateline\">Dec 2 (Reuters)</span><span class=\"tr-dl-sep\"> - </span>Abrdn PLC <a href=\"reuters://REALTIME/Verb=FullQuote/ric=ABDN.L\" data-type=\"ric\" data-ric=\"ABDN.L\" translate=\"no\" dir=\"ltr\">ABDN.L</a>:</p><ul class=\"bulleted-list arrowlist\"><li><p>ABRDN PLC  - ACQUISITION</p></li><li><p>ABRDN PLC - ABRDN ANNOUNCES PLANS TO ACQUIRE 100 PER CENT. OF UK'S LEADING SUBSCRIPTION-BASED INVESTMENT PLATFORM INTERACTIVE INVESTOR FOR \u00a31.49 BILLION.</p></li><li><p>ABRDN PLC - PLANS TO ACQUIRE 100 PER CENT. OF UK'S LEADING SUBSCRIPTION-BASED INVESTMENT PLATFORM INTERACTIVE INVESTOR FOR \u00a31.49 BILLION.</p></li><li><p>ABRDN PLC - AS PART OF ACQUISITION, RICHARD WILSON, CEO OF INTERACTIVE INVESTOR WILL JOIN ABRDN</p></li><li><p>ABRDN PLC - BOARD INTENDS TO MAINTAIN TOTAL DIVIDEND AT 14.6 PENCE PER ANNUM UNTIL IT IS COVERED AT LEAST 1.5 TIMES BY ADJUSTED CAPITAL GENERATION</p></li><li><p>ABRDN PLC - ACQUISITION WILL BE FUNDED IN CASH FROM ABRDN'S CAPITAL RESOURCES</p></li><li><p>ABRDN PLC - WE INTEND TO ISSUE ADDITIONAL TIER 1 DEBT OF C.\u00a3200 MILLION TO OPTIMISE OUR CAPITAL STRUCTURE</p></li><li><p>ABRDN PLC - INTENDS TO OPERATE INTERACTIVE INVESTOR AS A STANDALONE BUSINESS WITHIN ITS PERSONAL VECTOR</p></li><li><p>ABRDN PLC - ACQUISITION IS EXPECTED TO BE DOUBLE-DIGIT EARNINGS ACCRETIVE IN FIRST FULL FINANCIAL YEAR FOLLOWING COMPLETION</p></li><li><p>ABRDN PLC - CURRENTLY EXPECTED THAT COMPLETION OF ACQUISITION WILL OCCUR IN Q2 OF 2022</p></li></ul><p>Source text for Eikon: <span> (<a href=\"reuters://REALTIME/verb=NewsStory/ric=nRSB3704Ua\" data-type=\"storyId\" data-story-id=\"nRSB3704Ua\" translate=\"no\" dir=\"ltr\" class=\"tr-pnac\">Full Story</a>)</span></p><p>Further company coverage: <a href=\"reuters://REALTIME/verb=Headlines/ric=ABDN.L\" data-type=\"newsExpression\" data-expression=\"ABDN.L\" translate=\"no\" dir=\"ltr\">ABDN.L</a></p><p><br/></p><p class=\"tr-contactinfo\">(( <a href=\"mailto:Reuters.Briefs@thomsonreuters.com\" data-type=\"email\" translate=\"no\">Reuters.Briefs@thomsonreuters.com</a> ;;))</p><p class=\"line-break\"><br/></p><p class=\"tr-copyright\">(c) Copyright Thomson Reuters 2021. Click For Restrictions - https://agency.reuters.com/en/copyright.html</p></div>"}